docker_image_pin/__init__.py
docker_image_pin-0.4.2.dist-info/WHEEL
docker_image_pin-0.4.2.dist-info/entry_points.txt
docker_image_pin-0.4.2.dist-info/METADATA
docker_image_pin-0.4.2.dist-info/RECORD
