Metadata-Version: 2.4
Name: docker-image-pin
Version: 0.4.2
Summary: Checks if Docker images are properly pinned in docker-compose.yml and Dockerfile files
Author: GideonBear
License-Expression: GPL-3.0-only
Classifier: License :: OSI Approved :: GNU General Public License v3 (GPLv3)
Classifier: Programming Language :: Python :: 3 :: Only
Classifier: Programming Language :: Python :: 3.13
Requires-Python: >=3.13
Project-URL: bugs, https://github.com/GideonBear/docker-image-pin/issues
Project-URL: homepage, https://github.com/GideonBear/docker-image-pin
